README.md
setup.py
govai/__init__.py
govai.egg-info/PKG-INFO
govai.egg-info/SOURCES.txt
govai.egg-info/dependency_links.txt
govai.egg-info/not-zip-safe
govai.egg-info/top_level.txt