Metadata-Version: 1.0
Name: govai
Version: 0.0.0
Summary: ML Library
Home-page: http://github.com/INF800/govai
Author: Asapanna Rakesh
Author-email: rakeshark22@gmail.com
License: Apache v2
Platform: UNKNOWN
